Packages/__init__.py
Packages/my_module.py
Tests/Test_mymodule.py
Tests/__init__.py
DenemeGGGG-0.1.1.dist-info/LICENSE
DenemeGGGG-0.1.1.dist-info/METADATA
DenemeGGGG-0.1.1.dist-info/WHEEL
DenemeGGGG-0.1.1.dist-info/top_level.txt
DenemeGGGG-0.1.1.dist-info/RECORD
